gradiently/__init__.py
gradiently/compute/__init__.py
gradiently/compute/bundle_processing.py
gradiently/compute/compute_historical_features.py
gradiently/compute/df_loaders.py
gradiently/compute/entry.py
gradiently/compute/materialize_features.py
gradiently/core/__init__.py
gradiently/core/aggregation.py
gradiently/core/client.py
gradiently/core/configuration.py
gradiently/core/data_sources/file.py
gradiently/core/data_sources/registry.py
gradiently/core/data_sources/snowflake.py
gradiently/core/data_sources/source.py
gradiently/core/dtypes.py
gradiently/core/entity_key.py
gradiently/core/feature.py
gradiently/core/feature_bundle.py
gradiently/core/hash_utils.py
gradiently/core/obs_query.py
gradiently/core/spark_conf.py
gradiently/core/tests/test_serialization.py
gradiently/core/utils.py
gradiently/online_stores/__init__.py
gradiently/online_stores/base_store.py
gradiently/online_stores/redis_store.py
gradiently/registry/__init__.py
gradiently/registry/db_manager.py
gradiently/registry/envoy.yaml
gradiently/registry/grpc_server.py
gradiently/registry/models.py
gradiently/runtime/__init__.py
gradiently/runtime/constants.py
gradiently/runtime/databricks.py
gradiently/runtime/local.py
gradiently/runtime/packages.py
gradiently/runtime/runtime.py
gradiently/secrets/__init__.py
gradiently/secrets/aws_provider.py
gradiently/secrets/provider.py
gradiently/secrets/utils.py
gradiently-0.0.1.dist-info/METADATA
gradiently-0.0.1.dist-info/WHEEL
gradiently-0.0.1.dist-info/entry_points.txt
gradiently-0.0.1.dist-info/RECORD
