Metadata-Version: 2.1
Name: gradiently
Version: 0.0.1
Summary: 
Author: Andrew Tang
Author-email: atreeleaf@gmail.com
Requires-Python: >=3.9,<4.0
Classifier: Programming Language :: Python :: 3
Classifier: Programming Language :: Python :: 3.9
Classifier: Programming Language :: Python :: 3.10
Classifier: Programming Language :: Python :: 3.11
Requires-Dist: aioredis (>=2.0.1,<3.0.0)
Requires-Dist: alembic (>=1.11.1,<2.0.0)
Requires-Dist: boto3 (>=1.28.9,<2.0.0)
Requires-Dist: chardet (>=5.1.0,<6.0.0)
Requires-Dist: databricks-sdk (>=0.2.1,<0.3.0)
Requires-Dist: fastapi (>=0.100.0,<0.101.0)
Requires-Dist: furo (>=2023.7.26,<2024.0.0)
Requires-Dist: grpcio (>=1.56.0,<2.0.0)
Requires-Dist: grpcio-tools (>=1.56.0,<2.0.0)
Requires-Dist: pandas (>=2.0.3,<3.0.0)
Requires-Dist: protobuf (>=4.23.4,<5.0.0)
Requires-Dist: psycopg2 (>=2.9.6,<3.0.0)
Requires-Dist: psycopg2-binary (>=2.9.6,<3.0.0)
Requires-Dist: pyspark (==3.3.0)
Requires-Dist: python-docs-theme (>=2023.7,<2024.0)
Requires-Dist: pyyaml (>=6.0.1,<7.0.0)
Requires-Dist: redis (>=4.6.0,<5.0.0)
Requires-Dist: snowflake-connector-python (>=3.0.4,<4.0.0)
Requires-Dist: sphinx (>=7.1.2,<8.0.0)
Requires-Dist: sphinx-press-theme (>=0.8.0,<0.9.0)
